git_sensei/__init__.py
git_sensei/__main__.py
git_sensei/ai.py
git_sensei/cli.py
git_sensei/config.py
git_sensei/context.py
git_sensei/git_ops.py
git_sensei/safety.py
git_sensei-0.1.0.dist-info/licenses/LICENSE
git_sensei-0.1.0.dist-info/METADATA
git_sensei-0.1.0.dist-info/WHEEL
git_sensei-0.1.0.dist-info/entry_points.txt
git_sensei-0.1.0.dist-info/top_level.txt
git_sensei-0.1.0.dist-info/RECORD
